{
    "_id":  "a1b2c3d4e5f6b210",
    "name":  "Gilded Door Handle",
    "type":  "loot",
    "img":  "ionrift-data/overlays/ionrift-quartermaster/subscriber/art/items/terrain-treasure/gilded-door-handle.webp",
    "folder":  null,
    "system":  {
                   "description":  {
                                       "value":  "\u003cp\u003eRipped from its mount. Solid brass under gold leaf. Heavy, blunt, and unmistakably expensive for a door fitting.\u003c/p\u003e",
                                       "chat":  ""
                                   },
                   "source":  {
                                  "custom":  "",
                                  "book":  "Ionrift Quartermaster",
                                  "page":  "",
                                  "license":  ""
                              },
                   "quantity":  1,
                   "weight":  3,
                   "price":  {
                                 "value":  20,
                                 "denomination":  "gp"
                             },
                   "rarity":  "",
                   "identified":  true,
                   "properties":  [

                                  ],
                   "type":  {
                                "value":  "art",
                                "subtype":  ""
                            }
               },
    "flags":  {
                  "ionrift-workshop":  {
                                           "itemRef":  "ruins-gilded-door-handle",
                                           "coreMeta":  {
                                                            "category":  "Treasure",
                                                            "material":  "Treasure",
                                                            "priceGp":  20
                                                        }
                                       },
                  "ionrift-quartermaster":  {
                                                "terrain":  [
                                                                "ruins"
                                                            ]
                                            }
              }
}